[
    {
        "pictureSrc": "../partner/google.svg",
        "companyName": "Google",
        "companyDesc": "They have inspired us to become better at what our platform provides",
        "projects": [
            "Website Redesign and Development",
            "Digital Marketing Campaign",
            "Website Redesign and Development"
        ]
    },
    {
        "pictureSrc": "../partner/google.svg",
        "companyName": "Google",
        "companyDesc": "They have inspired us to become better at what our platform provides",
        "projects": [
            "Website Redesign and Development",
            "Digital Marketing Campaign",
            "Website Redesign and Development"
        ]
    },
    {
        "pictureSrc": "../partner/google.svg",
        "companyName": "Google",
        "companyDesc": "They have inspired us to become better at what our platform provides",
        "projects": [
            "Website Redesign and Development",
            "Digital Marketing Campaign",
            "Website Redesign and Development"
        ]
    },
    {
        "pictureSrc": "../partner/google.svg",
        "companyName": "Google",
        "companyDesc": "They have inspired us to become better at what our platform provides",
        "projects": [
            "Website Redesign and Development",
            "Digital Marketing Campaign",
            "Website Redesign and Development"
        ]
    }
]
